correlationplus/__init__.py
correlationplus/calculate.py
correlationplus/centralityAnalysis.py
correlationplus/pathAnalysis.py
correlationplus/visualize.py
correlationplus/scripts/__init__.py
correlationplus/scripts/analyze.py
correlationplus/scripts/calculate.py
correlationplus/scripts/correlationplus.py
correlationplus/scripts/diffMap.py
correlationplus/scripts/paths.py
correlationplus/scripts/visualize.py
correlationplus-0.2.1.dist-info/COPYING
correlationplus-0.2.1.dist-info/COPYING.LESSER
correlationplus-0.2.1.dist-info/METADATA
correlationplus-0.2.1.dist-info/WHEEL
correlationplus-0.2.1.dist-info/entry_points.txt
correlationplus-0.2.1.dist-info/top_level.txt
correlationplus-0.2.1.dist-info/RECORD
