Metadata-Version: 2.1
Name: correlationplus
Version: 0.2.1
Summary: A Python package to calculate, visualize and analyze correlations of proteins.
Home-page: https://github.com/tekpinar/correlationplus
Author: Mustafa Tekpinar
Author-email: tekpinar@buffalo.edu
License: LGPL
Download-URL: https://github.com/tekpinar/correlationplus
Platform: UNKNOWN
Classifier: Development Status :: 5 - Production/Stable
Classifier: Environment :: Console
Classifier: Operating System :: POSIX
Classifier: Operating System :: Microsoft :: Windows
Classifier: Programming Language :: Python :: 3
Classifier: Programming Language :: Python :: 3.6
Classifier: Programming Language :: Python :: 3.7
Classifier: Programming Language :: Python :: 3.8
Classifier: License :: OSI Approved :: GNU Lesser General Public License v3 (LGPLv3)
Classifier: Intended Audience :: Science/Research
Classifier: Topic :: Scientific/Engineering :: Bio-Informatics
Classifier: Topic :: Scientific/Engineering :: Chemistry
Requires-Python: >=3.6
License-File: COPYING
License-File: COPYING.LESSER
Requires-Dist: biopython (==1.76)
Requires-Dist: MDAnalysis (>=1.1.0)
Requires-Dist: matplotlib (<=3.3.4,>=3.2.2)
Requires-Dist: networkx (>=2.5.1)
Requires-Dist: prody
Requires-Dist: numba (>=0.50.0)
